valer.core.supermodel-1.2.4rc11-nspkg.pth
senaite/core/supermodel/__init__.py
senaite/core/supermodel/configure.zcml
senaite/core/supermodel/decorators.py
senaite/core/supermodel/interfaces.py
senaite/core/supermodel/model.py
senaite/core/supermodel/tests/__init__.py
senaite/core/supermodel/tests/base.py
senaite/core/supermodel/tests/test_doctests.py
senaite/core/supermodel/tests/test_setup.py
valer.core.supermodel-1.2.4rc11.dist-info/DESCRIPTION.rst
valer.core.supermodel-1.2.4rc11.dist-info/METADATA
valer.core.supermodel-1.2.4rc11.dist-info/RECORD
valer.core.supermodel-1.2.4rc11.dist-info/WHEEL
valer.core.supermodel-1.2.4rc11.dist-info/entry_points.txt
valer.core.supermodel-1.2.4rc11.dist-info/metadata.json
valer.core.supermodel-1.2.4rc11.dist-info/namespace_packages.txt
valer.core.supermodel-1.2.4rc11.dist-info/top_level.txt
